naparikro/__init__.py
naparikro/asyncrun.py
naparikro/helpers/__init__.py
naparikro/helpers/stage.py
naparikro/run.py
naparikro/widgets/main_widget.py
naparikro-0.1.8.dist-info/entry_points.txt
naparikro-0.1.8.dist-info/WHEEL
naparikro-0.1.8.dist-info/METADATA
naparikro-0.1.8.dist-info/RECORD
