Metadata-Version: 2.1
Name: naparikro
Version: 0.1.8
Summary: 
License: CC BY-NC 3.0
Author: jhnnsrs
Author-email: jhnnsrs@gmail.com
Requires-Python: >=3.7,<4.0
Classifier: License :: Other/Proprietary License
Classifier: Programming Language :: Python :: 3
Classifier: Programming Language :: Python :: 3.7
Classifier: Programming Language :: Python :: 3.8
Classifier: Programming Language :: Python :: 3.9
Requires-Dist: PyQt5 (>=5.15.4,<6.0.0)
Requires-Dist: PyQtWebEngine (>=5.15.4,<6.0.0)
Requires-Dist: arkitekt (>=0.1.18,<0.2.0)
Requires-Dist: mikro (>=0.1.18,<0.2.0)
Requires-Dist: napari (>=0.4.11,<0.5.0)
